wilhelminacli/__init__.py
wilhelminacli/cli.py
wilhelminacli/tests/__init__.py
wilhelminacli/tests/conftest.py
wilhelminacli/tests/test_cli.py
wilhelminacli/utils/__init__.py
wilhelminacli/utils/interactive.py
wilhelminacli/utils/summarizer.py
wilhelminacli-0.1.0.dist-info/LICENSE
wilhelminacli-0.1.0.dist-info/METADATA
wilhelminacli-0.1.0.dist-info/WHEEL
wilhelminacli-0.1.0.dist-info/entry_points.txt
wilhelminacli-0.1.0.dist-info/RECORD
