Metadata-Version: 2.1
Name: wilhelminacli
Version: 0.1.0
Summary: Command-line interface for Wilma school portal
Author: Frank
Author-email: frwickst@gmail.com
Requires-Python: >=3.13,<4.0
Classifier: Programming Language :: Python :: 3
Requires-Dist: anthropic (>=0.50.0,<0.51.0)
Requires-Dist: httpx (<0.28.0)
Requires-Dist: python-dotenv (>=1.1.0,<2.0.0)
Requires-Dist: rich (>=14.0.0,<15.0.0)
Requires-Dist: textual (>=3.1.1,<4.0.0)
Requires-Dist: typer (>=0.15.2,<0.16.0)
Requires-Dist: wilhelmina[aiohttp,playwright] (==0.1.3)
